[
    {
        "TerritoryID": "JtSJDpLTRzpzmzTMmtJW",
        "TerritoryDescription": "TerritoryDescription1",
        "RegionID": 1443823700
    },
    {
        "TerritoryID": "dpVHRvUzEtemiKvATqTC",
        "TerritoryDescription": "TerritoryDescription2",
        "RegionID": 1035407967
    },
    {
        "TerritoryID": "cZDIZGEAHCMKSRehsnjE",
        "TerritoryDescription": "TerritoryDescription3",
        "RegionID": 433306839
    },
    {
        "TerritoryID": "lzjknsIwDbcHLVTWknIx",
        "TerritoryDescription": "TerritoryDescription4",
        "RegionID": 172024010
    },
    {
        "TerritoryID": "WegEnonAxHmbKARdhcrZ",
        "TerritoryDescription": "TerritoryDescription5",
        "RegionID": 1969173190
    },
    {
        "TerritoryID": "JAJslUrizAQYbsxxJIJJ",
        "TerritoryDescription": "TerritoryDescription6",
        "RegionID": 1057175689
    },
    {
        "TerritoryID": "SvmGmWpHQeYfjfePuJLF",
        "TerritoryDescription": "TerritoryDescription7",
        "RegionID": 1579171424
    },
    {
        "TerritoryID": "xdLKgFwatYTPaguJKGGM",
        "TerritoryDescription": "TerritoryDescription8",
        "RegionID": 1663551251
    },
    {
        "TerritoryID": "BDfXwrANrSGEdqBmLatB",
        "TerritoryDescription": "TerritoryDescription9",
        "RegionID": 1797658252
    },
    {
        "TerritoryID": "apDLNjmjUHFJWcqaHKwq",
        "TerritoryDescription": "TerritoryDescription10",
        "RegionID": 1463724878
    },
    {
        "TerritoryID": "sSGgVIGLYrXsASJicmWn",
        "TerritoryDescription": "TerritoryDescription11",
        "RegionID": 1569397238
    },
    {
        "TerritoryID": "hlHSIhfRzJaiJbylRpaT",
        "TerritoryDescription": "TerritoryDescription12",
        "RegionID": 1968616624
    },
    {
        "TerritoryID": "LtOAYmgnPMWsTxBbDuMp",
        "TerritoryDescription": "TerritoryDescription13",
        "RegionID": 631114002
    },
    {
        "TerritoryID": "hncChhyxorIjgQonooCV",
        "TerritoryDescription": "TerritoryDescription14",
        "RegionID": 1222925059
    },
    {
        "TerritoryID": "VJShFHgCtehHvMuylnVr",
        "TerritoryDescription": "TerritoryDescription15",
        "RegionID": 958329571
    },
    {
        "TerritoryID": "SqNLDTrAuZbtnVwiJbaG",
        "TerritoryDescription": "TerritoryDescription16",
        "RegionID": 675182397
    },
    {
        "TerritoryID": "xQbgJPfoeqSipMLTqMLX",
        "TerritoryDescription": "TerritoryDescription17",
        "RegionID": 1903747116
    },
    {
        "TerritoryID": "MdBNmXzlwnfYuDARLNFf",
        "TerritoryDescription": "TerritoryDescription18",
        "RegionID": 567159491
    },
    {
        "TerritoryID": "RLxCrWiebDcVcLWPDprH",
        "TerritoryDescription": "TerritoryDescription19",
        "RegionID": 1684257870
    },
    {
        "TerritoryID": "tCyNzWTryhxkWYosxLNS",
        "TerritoryDescription": "TerritoryDescription20",
        "RegionID": 1090148904
    },
    {
        "TerritoryID": "zolYaPmqkiLJPuQyXRSV",
        "TerritoryDescription": "TerritoryDescription21",
        "RegionID": 1072516823
    },
    {
        "TerritoryID": "LcaOXVWAwuTAmErkoHbL",
        "TerritoryDescription": "TerritoryDescription22",
        "RegionID": 2009585286
    },
    {
        "TerritoryID": "ksMxWWioeowAspqRWwKX",
        "TerritoryDescription": "TerritoryDescription23",
        "RegionID": 2127629537
    },
    {
        "TerritoryID": "kkvWfpaGAAgeopEauqTP",
        "TerritoryDescription": "TerritoryDescription24",
        "RegionID": 1252356741
    },
    {
        "TerritoryID": "eoAQOMQhnYQZfpZTeDaj",
        "TerritoryDescription": "TerritoryDescription25",
        "RegionID": 410443902
    },
    {
        "TerritoryID": "KAnwBsYNyQtbeMxhNfaz",
        "TerritoryDescription": "TerritoryDescription26",
        "RegionID": 9811483
    },
    {
        "TerritoryID": "TCWWfmeQfdaUIhdLhPeU",
        "TerritoryDescription": "TerritoryDescription27",
        "RegionID": 1422947665
    },
    {
        "TerritoryID": "zvrwRSJMkRTlhsJmsSOb",
        "TerritoryDescription": "TerritoryDescription28",
        "RegionID": 357951019
    },
    {
        "TerritoryID": "SHgeEcorvfKMFoOqBdJA",
        "TerritoryDescription": "TerritoryDescription29",
        "RegionID": 1774776457
    },
    {
        "TerritoryID": "ZmmyArqLwyoeDFJTLwcy",
        "TerritoryDescription": "TerritoryDescription30",
        "RegionID": 2091284793
    },
    {
        "TerritoryID": "InnnoRCHCRpSPFOKcWCF",
        "TerritoryDescription": "TerritoryDescription31",
        "RegionID": 2122732351
    },
    {
        "TerritoryID": "OxTHfJjvKtMVbqyasWZT",
        "TerritoryDescription": "TerritoryDescription32",
        "RegionID": 186888259
    },
    {
        "TerritoryID": "RHVorABINkNyoDUBCPtG",
        "TerritoryDescription": "TerritoryDescription33",
        "RegionID": 2144158827
    },
    {
        "TerritoryID": "mACBdcoiunxIUWxssQlM",
        "TerritoryDescription": "TerritoryDescription34",
        "RegionID": 1830685468
    },
    {
        "TerritoryID": "eArNAtehgxTMzkfFCVbR",
        "TerritoryDescription": "TerritoryDescription35",
        "RegionID": 1244935901
    },
    {
        "TerritoryID": "qwylliWzojqBcKjcouiL",
        "TerritoryDescription": "TerritoryDescription36",
        "RegionID": 601368835
    },
    {
        "TerritoryID": "EPBjUjJjiRiUgrYXGpKm",
        "TerritoryDescription": "TerritoryDescription37",
        "RegionID": 481866516
    },
    {
        "TerritoryID": "DqQIEZvveIdepaenGAXP",
        "TerritoryDescription": "TerritoryDescription38",
        "RegionID": 3447163
    },
    {
        "TerritoryID": "HdCXWDBsnKPrroSppPAe",
        "TerritoryDescription": "TerritoryDescription39",
        "RegionID": 1045760229
    },
    {
        "TerritoryID": "EhXlRDiqagraCOPkIdCk",
        "TerritoryDescription": "TerritoryDescription40",
        "RegionID": 327535826
    }
]